semestr1580.py
semestr1580-0.1.0.dist-info/WHEEL
semestr1580-0.1.0.dist-info/METADATA
semestr1580-0.1.0.dist-info/RECORD
